README.md
setup.py
pracode/__init__.py
pracode/lcwrapper.py
pracode/main.py
pracode/util.py
pracode.egg-info/PKG-INFO
pracode.egg-info/SOURCES.txt
pracode.egg-info/dependency_links.txt
pracode.egg-info/entry_points.txt
pracode.egg-info/requires.txt
pracode.egg-info/top_level.txt