Metadata-Version: 1.1
Name: pracode
Version: 0.1.0
Summary: tool for practicing coding skills against coding websites, e.g. leetcode, etc.
Home-page: https://github.com/yhcharles/pracode
Author: Charlie Yan
Author-email: UNKNOWN
License: UNKNOWN
Platform: UNKNOWN
Classifier: Programming Language :: Python :: 3 :: Only
